{"nodes": [{"id": "c_xampp_htdocs_prasccenter_app_models_servicios_php", "label": "Servicios.php", "file_type": "code", "source_file": "C:\\xampp\\htdocs\\PrascCenter\\app\\Models\\Servicios.php", "source_location": "L1"}, {"id": "models_servicios_servicios", "label": "Servicios", "file_type": "code", "source_file": "C:\\xampp\\htdocs\\PrascCenter\\app\\Models\\Servicios.php", "source_location": "L9"}, {"id": "model", "label": "Model", "file_type": "code", "source_file": "", "source_location": ""}, {"id": "hasfactory", "label": "HasFactory", "file_type": "code", "source_file": "", "source_location": ""}, {"id": "models_servicios_servicios_buscaservicioventa", "label": ".buscaServicioVenta()", "file_type": "code", "source_file": "C:\\xampp\\htdocs\\PrascCenter\\app\\Models\\Servicios.php", "source_location": "L13"}, {"id": "models_servicios_servicios_eliminarservicioventa", "label": ".eliminarServicioVenta()", "file_type": "code", "source_file": "C:\\xampp\\htdocs\\PrascCenter\\app\\Models\\Servicios.php", "source_location": "L31"}], "edges": [{"source": "c_xampp_htdocs_prasccenter_app_models_servicios_php", "target": "hasfactory", "relation": "imports", "context": "import", "confidence": "EXTRACTED", "source_file": "C:\\xampp\\htdocs\\PrascCenter\\app\\Models\\Servicios.php", "source_location": "L5", "weight": 1.0}, {"source": "c_xampp_htdocs_prasccenter_app_models_servicios_php", "target": "model", "relation": "imports", "context": "import", "confidence": "EXTRACTED", "source_file": "C:\\xampp\\htdocs\\PrascCenter\\app\\Models\\Servicios.php", "source_location": "L6", "weight": 1.0}, {"source": "c_xampp_htdocs_prasccenter_app_models_servicios_php", "target": "db", "relation": "imports", "context": "import", "confidence": "EXTRACTED", "source_file": "C:\\xampp\\htdocs\\PrascCenter\\app\\Models\\Servicios.php", "source_location": "L7", "weight": 1.0}, {"source": "c_xampp_htdocs_prasccenter_app_models_servicios_php", "target": "models_servicios_servicios", "relation": "contains", "confidence": "EXTRACTED", "source_file": "C:\\xampp\\htdocs\\PrascCenter\\app\\Models\\Servicios.php", "source_location": "L9", "weight": 1.0}, {"source": "models_servicios_servicios", "target": "model", "relation": "inherits", "confidence": "EXTRACTED", "source_file": "C:\\xampp\\htdocs\\PrascCenter\\app\\Models\\Servicios.php", "source_location": "L9", "weight": 1.0}, {"source": "models_servicios_servicios", "target": "hasfactory", "relation": "mixes_in", "confidence": "EXTRACTED", "source_file": "C:\\xampp\\htdocs\\PrascCenter\\app\\Models\\Servicios.php", "source_location": "L11", "weight": 1.0}, {"source": "models_servicios_servicios", "target": "models_servicios_servicios_buscaservicioventa", "relation": "method", "confidence": "EXTRACTED", "source_file": "C:\\xampp\\htdocs\\PrascCenter\\app\\Models\\Servicios.php", "source_location": "L13", "weight": 1.0}, {"source": "models_servicios_servicios", "target": "models_servicios_servicios_eliminarservicioventa", "relation": "method", "confidence": "EXTRACTED", "source_file": "C:\\xampp\\htdocs\\PrascCenter\\app\\Models\\Servicios.php", "source_location": "L31", "weight": 1.0}], "raw_calls": [{"caller_nid": "models_servicios_servicios_buscaservicioventa", "callee": "first", "is_member_call": true, "source_file": "C:\\xampp\\htdocs\\PrascCenter\\app\\Models\\Servicios.php", "source_location": "L15"}, {"caller_nid": "models_servicios_servicios_buscaservicioventa", "callee": "where", "is_member_call": true, "source_file": "C:\\xampp\\htdocs\\PrascCenter\\app\\Models\\Servicios.php", "source_location": "L15"}, {"caller_nid": "models_servicios_servicios_buscaservicioventa", "callee": "table", "is_member_call": true, "source_file": "C:\\xampp\\htdocs\\PrascCenter\\app\\Models\\Servicios.php", "source_location": "L15"}, {"caller_nid": "models_servicios_servicios_buscaservicioventa", "callee": "DB", "is_member_call": false, "source_file": "C:\\xampp\\htdocs\\PrascCenter\\app\\Models\\Servicios.php", "source_location": "L15"}, {"caller_nid": "models_servicios_servicios_buscaservicioventa", "callee": "first", "is_member_call": true, "source_file": "C:\\xampp\\htdocs\\PrascCenter\\app\\Models\\Servicios.php", "source_location": "L21"}, {"caller_nid": "models_servicios_servicios_buscaservicioventa", "callee": "where", "is_member_call": true, "source_file": "C:\\xampp\\htdocs\\PrascCenter\\app\\Models\\Servicios.php", "source_location": "L21"}, {"caller_nid": "models_servicios_servicios_buscaservicioventa", "callee": "table", "is_member_call": true, "source_file": "C:\\xampp\\htdocs\\PrascCenter\\app\\Models\\Servicios.php", "source_location": "L21"}, {"caller_nid": "models_servicios_servicios_buscaservicioventa", "callee": "DB", "is_member_call": false, "source_file": "C:\\xampp\\htdocs\\PrascCenter\\app\\Models\\Servicios.php", "source_location": "L21"}, {"caller_nid": "models_servicios_servicios_eliminarservicioventa", "callee": "update", "is_member_call": true, "source_file": "C:\\xampp\\htdocs\\PrascCenter\\app\\Models\\Servicios.php", "source_location": "L33"}, {"caller_nid": "models_servicios_servicios_eliminarservicioventa", "callee": "where", "is_member_call": true, "source_file": "C:\\xampp\\htdocs\\PrascCenter\\app\\Models\\Servicios.php", "source_location": "L33"}, {"caller_nid": "models_servicios_servicios_eliminarservicioventa", "callee": "table", "is_member_call": true, "source_file": "C:\\xampp\\htdocs\\PrascCenter\\app\\Models\\Servicios.php", "source_location": "L33"}, {"caller_nid": "models_servicios_servicios_eliminarservicioventa", "callee": "DB", "is_member_call": false, "source_file": "C:\\xampp\\htdocs\\PrascCenter\\app\\Models\\Servicios.php", "source_location": "L33"}, {"caller_nid": "models_servicios_servicios_eliminarservicioventa", "callee": "delete", "is_member_call": true, "source_file": "C:\\xampp\\htdocs\\PrascCenter\\app\\Models\\Servicios.php", "source_location": "L39"}, {"caller_nid": "models_servicios_servicios_eliminarservicioventa", "callee": "where", "is_member_call": true, "source_file": "C:\\xampp\\htdocs\\PrascCenter\\app\\Models\\Servicios.php", "source_location": "L39"}, {"caller_nid": "models_servicios_servicios_eliminarservicioventa", "callee": "table", "is_member_call": true, "source_file": "C:\\xampp\\htdocs\\PrascCenter\\app\\Models\\Servicios.php", "source_location": "L39"}, {"caller_nid": "models_servicios_servicios_eliminarservicioventa", "callee": "DB", "is_member_call": false, "source_file": "C:\\xampp\\htdocs\\PrascCenter\\app\\Models\\Servicios.php", "source_location": "L39"}]}